{
	"all": {
		"include": {
			"all": [
				"android-tools",
				"apr",
				"apr-util",
				"autojump",
				"bluez-obexd",
				"btop",
				"cargo",
				"distrobox",
				"ffmpeg",
				"ffmpeg-libs",
				"fzf",
				"gh",
				"go",
				"goverlay",
				"heimdall",
				"htop",
				"igt-gpu-tools",
				"intel-media-driver",
				"intel-mediasdk",
				"just",
				"libratbag-ratbagd",
				"libva-intel-driver",
				"libva-utils",
				"lz4",
				"make",
				"mangohud",
				"mpv",
				"neofetch",
				"neovim",
				"nvtop",
				"openrgb-udev-rules",
				"openssl",
				"podman-compose",
				"pipewire-codec-aptx",
				"rust",
				"rustfmt",
				"smartmontools",
				"tmux",
				"virt-install",
				"virt-manager",
				"virt-viewer",
				"vulkan-tools",
				"vkBasalt",
				"zstd"
			],
			"gahnite": [
				"ffmpegthumbnailer",
				"gnome-tweaks",
				"gnome-console",
				"pop-shell"
			],
			"hypersthene": [
				"dex-autostart",
				"dolphin",
				"dunst",
				"ffmpegthumbs",
				"hyprland",
				"light",
				"kdegraphics-thumbnailers",
				"kitty",
				"kvantum",
				"polkit-kde",
				"qt5ct",
				"rofi-wayland",
				"sddm",
				"waybar",
				"wlogout",
				"wlr-randr",
				"xdg-desktop-portal-hyprland",
				"xdg-user-dirs"
			],
			"kinoite": [
				"bismuth",
				"materia-kde"
			],
			"sphene": [
				"ark",
				"dex-autostart",
				"dmenu",
				"dolphin",
				"ffmpegthumbs",
				"flatpak-xdg-utils",
				"kdegraphics-thumbnailers",
				"kde-partitionmanager",
				"kitty",
				"kvantum",
				"materia-kde-sddm",
				"polkit-kde",
				"qt5ct",
				"sddm-themes",
				"wdisplays",
				"wf-recorder",
				"wlogout",
				"wlr-randr",
				"wlogout",
				"xdg-desktop-portal-kde"
			]
		},
		"exclude": {
			"all": [
				"default-editor",
				"firefox",
				"firefox-langpacks",
				"libavcodec-free",
				"libavdevice-free",
				"libavfilter-free",
				"libavformat-free",
				"libavutil-free",
				"libpostproc-free",
				"libswresample-free",
				"libswscale-free",
				"nano",
				"nano-default-editor",
				"vim-common",
				"vim-default-editor",
				"vim-enhanced"
			],
			"gahnite": [
				"gnome-terminal",
				"gnome-terminal-nautilus"
			],
			"hypersthene": [
				"xdg-desktop-portal-gtk"
			],
			"kinoite": [],
			"sphene": [
				"foot",
				"foot-term",
				"lxqt-policykit",
				"liblxqt",
				"sway-config-fedora",
				"Thunar",
				"thunar-archive-plugin"
			]
		}
	},
	"38": {
		"include": {
			"all": [
				"mesa-va-drivers-freeworld"
			],
			"gahnite": [],
			"hypersthene": [
				"f38-backgrounds-base",
				"f38-backgrounds-extras-base"
			],
			"kinoite": [],
			"sphene": [
				"f38-backgrounds-extras-base",
				"qt6ct"
			]
		},
		"exclude": {
			"all": [
				"mesa-va-drivers"
			],
			"gahnite": [],
			"hypersthene": [],
			"kinoite": [],
			"sphene": []
		}
	},
	"rawhide": {
		"include": {
			"all": [
				"mesa-filesystem"
			],
			"gahnite": [],
			"hypersthene": [
				"libxcrypt"
			],
			"kinoite": [],
			"sphene": [
				"libxcrypt",
				"xdg-desktop-portal-hyprland"
			]
		},
		"exclude": {
			"all": [],
			"gahnite": [],
			"hypersthene": [
				"libxcrypt"
			],
			"kinoite": [],
			"sphene": [
				"libxcrypt",
				"xdg-desktop-portal-wlr"
			]
		}
	}
}
